LICENSE
MANIFEST.in
README.md
setup.cfg
setup.py
docassemble/__init__.py
docassemble.NDA.egg-info/PKG-INFO
docassemble.NDA.egg-info/SOURCES.txt
docassemble.NDA.egg-info/dependency_links.txt
docassemble.NDA.egg-info/namespace_packages.txt
docassemble.NDA.egg-info/not-zip-safe
docassemble.NDA.egg-info/top_level.txt
docassemble/NDA/__init__.py
docassemble/NDA/data/questions/NDA.yml
docassemble/NDA/data/sources/README.md
docassemble/NDA/data/static/README.md
docassemble/NDA/data/templates/LLAW3254_LITE_Student_undertaking_on_confidentiality_and_conflicts_2.docx
docassemble/NDA/data/templates/README.md